Metadata-Version: 2.1
Name: simplewave
Version: 0.1.0
Summary: Simple Wave file read and write module
Home-page: https://github.com/lotcarnage/simplewave
Author: lotcarnage
Author-email: lotcarnage@gmail.com
License: MIT
Platform: UNKNOWN
Requires-Python: >=3.8
License-File: LICENSE
